dtmm/A.dat
dtmm/CIE1931XYZ.dat
dtmm/CIE1964XYZ.dat
dtmm/CIE2006-10XYZ.dat
dtmm/CIE2006-2XYZ.dat
dtmm/CMOSY.dat
dtmm/D65.dat
dtmm/__init__.py
dtmm/color.py
dtmm/conf.py
dtmm/data.py
dtmm/data_viewer.py
dtmm/denoise.py
dtmm/diffract.py
dtmm/dtmm.ini
dtmm/fft.py
dtmm/field.py
dtmm/field_viewer.py
dtmm/hashing.py
dtmm/jones.py
dtmm/jones4.py
dtmm/linalg.py
dtmm/matrix.py
dtmm/mode.py
dtmm/print_tools.py
dtmm/propagate_2x2.py
dtmm/propagate_4x4.py
dtmm/rotation.py
dtmm/tmm.py
dtmm/tmm2d.py
dtmm/tmm3d.py
dtmm/transfer.py
dtmm/wave.py
dtmm/window.py
dtmm/test/__init__.py
dtmm/test/test_data.py
dtmm/test/test_fft.py
dtmm/test/test_linalg.py
dtmm/test/test_tmm.py
dtmm/test/test_wave.py
dtmm-0.6.1.dist-info/LICENSE
dtmm-0.6.1.dist-info/METADATA
dtmm-0.6.1.dist-info/WHEEL
dtmm-0.6.1.dist-info/top_level.txt
dtmm-0.6.1.dist-info/RECORD
