Metadata-Version: 2.1
Name: dtmm
Version: 0.6.1
Summary: Diffractive Transfer Matrix Method
Home-page: https://github.com/IJSComplexMatter/dtmm
Author: Andrej Petelin
Author-email: andrej.petelin@gmail.com
License: UNKNOWN
Platform: UNKNOWN
Classifier: Programming Language :: Python :: 3
Classifier: License :: OSI Approved :: MIT License
Classifier: Operating System :: OS Independent
